diot/__init__.py
diot/diot.py
diot/py.typed
diot/transforms.py
diot/utils.py
diot-0.3.2.dist-info/LICENSE
diot-0.3.2.dist-info/METADATA
diot-0.3.2.dist-info/WHEEL
diot-0.3.2.dist-info/RECORD
