Metadata-Version: 2.3
Name: diot
Version: 0.3.2
Summary: Python dictionary with dot notation.
License: MIT
Author: pwwang
Author-email: pwwang@pwwang.com
Requires-Python: >=3.9,<4.0
Classifier: License :: OSI Approved :: MIT License
Classifier: Programming Language :: Python :: 3
Classifier: Programming Language :: Python :: 3.9
Classifier: Programming Language :: Python :: 3.10
Classifier: Programming Language :: Python :: 3.11
Classifier: Programming Language :: Python :: 3.12
Classifier: Programming Language :: Python :: 3.13
Provides-Extra: all
Provides-Extra: toml
Provides-Extra: yaml
Requires-Dist: inflection (>=0.5,<0.6)
Requires-Dist: pyyaml (>=6,<7) ; extra == "yaml" or extra == "all"
Requires-Dist: rtoml (>=0.12,<0.13) ; (sys_platform == "linux") and (extra == "toml" or extra == "all")
Requires-Dist: tomli (>=2.0,<3.0) ; (sys_platform != "linux") and (extra == "toml" or extra == "all")
Project-URL: Homepage, https://github.com/pwwang/diot
Project-URL: Repository, https://github.com/pwwang/diot
